cupy/__init__.py
cupy/_environment.py
cupy/_util.cp39-win_amd64.pyd
cupy/_version.py
cupy/cublas.py
cupy/cudnn.cp39-win_amd64.pyd
cupy/cusolver.cp39-win_amd64.pyd
cupy/cusparse.py
cupy/cutensor.cp39-win_amd64.pyd
cupy/.data/_wheel.json
cupy/.data/lib/nvToolsExt64_1.dll
cupy/_binary/__init__.py
cupy/_binary/elementwise.py
cupy/_binary/packing.py
cupy/_core/__init__.py
cupy/_core/_accelerator.cp39-win_amd64.pyd
cupy/_core/_carray.cp39-win_amd64.pyd
cupy/_core/_codeblock.py
cupy/_core/_cub_reduction.cp39-win_amd64.pyd
cupy/_core/_dtype.cp39-win_amd64.pyd
cupy/_core/_fusion_interface.py
cupy/_core/_fusion_kernel.cp39-win_amd64.pyd
cupy/_core/_fusion_op.py
cupy/_core/_fusion_optimization.py
cupy/_core/_fusion_thread_local.cp39-win_amd64.pyd
cupy/_core/_fusion_trace.cp39-win_amd64.pyd
cupy/_core/_fusion_variable.cp39-win_amd64.pyd
cupy/_core/_gufuncs.py
cupy/_core/_kernel.cp39-win_amd64.pyd
cupy/_core/_memory_range.cp39-win_amd64.pyd
cupy/_core/_optimize_config.cp39-win_amd64.pyd
cupy/_core/_reduction.cp39-win_amd64.pyd
cupy/_core/_routines_binary.cp39-win_amd64.pyd
cupy/_core/_routines_indexing.cp39-win_amd64.pyd
cupy/_core/_routines_linalg.cp39-win_amd64.pyd
cupy/_core/_routines_logic.cp39-win_amd64.pyd
cupy/_core/_routines_manipulation.cp39-win_amd64.pyd
cupy/_core/_routines_math.cp39-win_amd64.pyd
cupy/_core/_routines_sorting.cp39-win_amd64.pyd
cupy/_core/_routines_statistics.cp39-win_amd64.pyd
cupy/_core/_scalar.cp39-win_amd64.pyd
cupy/_core/_ufuncs.py
cupy/_core/core.cp39-win_amd64.pyd
cupy/_core/dlpack.cp39-win_amd64.pyd
cupy/_core/flags.cp39-win_amd64.pyd
cupy/_core/fusion.cp39-win_amd64.pyd
cupy/_core/internal.cp39-win_amd64.pyd
cupy/_core/new_fusion.cp39-win_amd64.pyd
cupy/_core/raw.cp39-win_amd64.pyd
cupy/_core/syncdetect.py
cupy/_core/include/cupy/README.md
cupy/_core/include/cupy/atomics.cuh
cupy/_core/include/cupy/carray.cuh
cupy/_core/include/cupy/complex.cuh
cupy/_core/include/cupy/cuComplex_bridge.h
cupy/_core/include/cupy/hip_workaround.cuh
cupy_cuda101-9.6.0.dist-info/METADATA
cupy_cuda101-9.6.0.dist-info/WHEEL
cupy_cuda101-9.6.0.dist-info/license.rst
cupy_cuda101-9.6.0.dist-info/top_level.txt
cupy_cuda101-9.6.0.dist-info/RECORD
